ctmango/MClass.py
ctmango/__init__.py
ctmango/mdef.py
ctmango-0.0.1.dist-info/METADATA
ctmango-0.0.1.dist-info/WHEEL
ctmango-0.0.1.dist-info/top_level.txt
ctmango-0.0.1.dist-info/RECORD
