Metadata-Version: 2.1
Name: ctmango
Version: 0.0.1
Summary: A nice project
Home-page: https://github.com/nsdimitriadis/ctmango
Author: Nikos Dimitriadis
Author-email: nsdimitriadis@gmail.com
License: None
Platform: UNKNOWN
